{
  "items": [
    {
      "id": "imdb-tt37287335",
      "imdbId": "tt37287335",
      "title": "Obsession",
      "description": "After breaking the mysterious \"One Wish Willow\" to win his crush's heart, a hopeless romantic finds himself getting exactly what he asked for but soon discovers that some desires come at a dark, sinister price.",
      "coverImage": "https://m.media-amazon.com/images/M/MV5BYzc1NWUwMDgtNGZlMS00ZmYzLWIzMzktNmMxMmY1MTUzNWExXkEyXkFqcGc@._V1_UY500_AL_QL75_UX380_CR0,0,380,562_.jpg",
      "backdropImage": "https://m.media-amazon.com/images/M/MV5BYzc1NWUwMDgtNGZlMS00ZmYzLWIzMzktNmMxMmY1MTUzNWExXkEyXkFqcGc@._V1_UY1280_AL_QL75_UX380_CR0,0,380,562_.jpg",
      "year": 2026,
      "rating": 8.2,
      "genre": "Horror, Romance, Thriller",
      "type": "movie",
      "maturity": "R",
      "featured": true,
      "local": false
    },
    {
      "id": "imdb-tt15047880",
      "imdbId": "tt15047880",
      "title": "Disclosure Day",
      "description": "If you found out we weren't alone, if someone showed you, proved it to you, would that frighten you?",
      "coverImage": "https://m.media-amazon.com/images/M/MV5BMTgwNDI1ZjctYWNmMS00MTJhLTg1ZWItMzI1Yjk5NjZkYWFkXkEyXkFqcGc@._V1_UY500_AL_QL75_UX380_CR0,20,380,562_.jpg",
      "backdropImage": "https://m.media-amazon.com/images/M/MV5BMTgwNDI1ZjctYWNmMS00MTJhLTg1ZWItMzI1Yjk5NjZkYWFkXkEyXkFqcGc@._V1_UY1280_AL_QL75_UX380_CR0,20,380,562_.jpg",
      "year": 2026,
      "rating": 0,
      "genre": "Drama, Sci-Fi, Thriller",
      "type": "movie",
      "maturity": "PG-13",
      "featured": true,
      "local": false
    },
    {
      "id": "imdb-tt29355505",
      "imdbId": "tt29355505",
      "title": "Toy Story 5",
      "description": "Woody, Buzz, Jessie and the rest of the gang's jobs are challenged when they're introduced to electronics, a new threat to playtime.",
      "coverImage": "https://m.media-amazon.com/images/M/MV5BZTI1YTBiNmEtYWUxZi00YzFkLWIzNjMtMmZjMmY2NzM0ZWMzXkEyXkFqcGc@._V1_UY500_AL_QL75_UX380_CR0,0,380,562_.jpg",
      "backdropImage": "https://m.media-amazon.com/images/M/MV5BZTI1YTBiNmEtYWUxZi00YzFkLWIzNjMtMmZjMmY2NzM0ZWMzXkEyXkFqcGc@._V1_UY1280_AL_QL75_UX380_CR0,0,380,562_.jpg",
      "year": 2026,
      "rating": 0,
      "genre": "Animation, Adventure, Comedy",
      "type": "movie",
      "maturity": "PG",
      "featured": true,
      "local": false
    },
    {
      "id": "imdb-tt10375624",
      "imdbId": "tt10375624",
      "title": "Voicemails for Isabelle",
      "description": "Jill leaves voice messages to her deceased sister telling her about her chaotic life in San Francisco. Unwittingly, a mysterious Austin real estate agent begins to receive their confessions..",
      "coverImage": "",
      "backdropImage": "",
      "year": 2026,
      "rating": 0,
      "genre": "Comedy, Romance",
      "type": "movie",
      "maturity": "N/A",
      "featured": true,
      "local": false
    },
    {
      "id": "imdb-tt26657236",
      "imdbId": "tt26657236",
      "title": "Backrooms",
      "description": "After a therapist's patient disappears into a dimension beyond reality, she must venture into the unknown to save him.",
      "coverImage": "https://m.media-amazon.com/images/M/MV5BYzQyYjZmMjctMzIyZi00MDI0LWJhNGQtMzQ3MTFlNDgwNGM5XkEyXkFqcGc@._V1_UY500_AL_QL75_UX380_CR0,0,380,562_.jpg",
      "backdropImage": "https://m.media-amazon.com/images/M/MV5BYzQyYjZmMjctMzIyZi00MDI0LWJhNGQtMzQ3MTFlNDgwNGM5XkEyXkFqcGc@._V1_UY1280_AL_QL75_UX380_CR0,0,380,562_.jpg",
      "year": 2026,
      "rating": 7.1,
      "genre": "Horror, Sci-Fi, Thriller",
      "type": "movie",
      "maturity": "R",
      "featured": true,
      "local": false
    },
    {
      "id": "imdb-tt11378946",
      "imdbId": "tt11378946",
      "title": "Michael",
      "description": "The early life of musician Michael Jackson, from the discovery of his talent as the lead of the Jackson Five to the artist whose creative ambition fueled a pursuit to become the biggest entertainer in the world.",
      "coverImage": "https://m.media-amazon.com/images/M/MV5BNzllNmRlN2EtMDQyOC00ODJjLTg4OWQtZDNmNGU3YzlkNjc1XkEyXkFqcGc@._V1_UY500_AL_QL75_UX380_CR0,0,380,562_.jpg",
      "backdropImage": "https://m.media-amazon.com/images/M/MV5BNzllNmRlN2EtMDQyOC00ODJjLTg4OWQtZDNmNGU3YzlkNjc1XkEyXkFqcGc@._V1_UY1280_AL_QL75_UX380_CR0,0,380,562_.jpg",
      "year": 2026,
      "rating": 7.7,
      "genre": "Biography, Drama, History",
      "type": "movie",
      "maturity": "PG-13",
      "featured": true,
      "local": false
    },
    {
      "id": "imdb-tt0427340",
      "imdbId": "tt0427340",
      "title": "Masters of the Universe",
      "description": "A young man on Earth discovers a fabulous secret legacy as the prince of an alien planet, and must recover a magic sword and return home to protect his kingdom.",
      "coverImage": "https://m.media-amazon.com/images/M/MV5BMTJjYTFkM2EtZjBmNy00OTk2LTg0NTAtNzYxYzlmNjhkMzQ5XkEyXkFqcGc@._V1_UY500_AL_QL75_UX380_CR0,0,380,562_.jpg",
      "backdropImage": "https://m.media-amazon.com/images/M/MV5BMTJjYTFkM2EtZjBmNy00OTk2LTg0NTAtNzYxYzlmNjhkMzQ5XkEyXkFqcGc@._V1_UY1280_AL_QL75_UX380_CR0,0,380,562_.jpg",
      "year": 2026,
      "rating": 0,
      "genre": "Action, Adventure, Fantasy",
      "type": "movie",
      "maturity": "PG-13",
      "featured": true,
      "local": false
    },
    {
      "id": "imdb-tt22084616",
      "imdbId": "tt22084616",
      "title": "Spider-Man: Brand New Day",
      "description": "A forgotten Peter Parker lives alone as a full-time Spider-Man until mounting pressure triggers a dangerous change and a powerful new enemy emerges.",
      "coverImage": "https://m.media-amazon.com/images/M/MV5BOWNjYWM3NWItOGE0ZS00MWRjLThiZWEtYjc4ZmNmMmU5ZTVmXkEyXkFqcGc@._V1_UY500_AL_QL75_UX380_CR0,0,380,562_.jpg",
      "backdropImage": "https://m.media-amazon.com/images/M/MV5BOWNjYWM3NWItOGE0ZS00MWRjLThiZWEtYjc4ZmNmMmU5ZTVmXkEyXkFqcGc@._V1_UY1280_AL_QL75_UX380_CR0,0,380,562_.jpg",
      "year": 2026,
      "rating": 0,
      "genre": "Action, Adventure, Fantasy",
      "type": "movie",
      "maturity": "N/A",
      "featured": true,
      "local": false
    },
    {
      "id": "imdb-tt12042730",
      "imdbId": "tt12042730",
      "title": "Project Hail Mary",
      "description": "A science teacher wakes up alone on a spaceship. As his memory returns, he uncovers a mission to stop a mysterious substance killing Earth's sun, and realizes that an unexpected friendship may be the key.",
      "coverImage": "https://m.media-amazon.com/images/M/MV5BNTkwNzJiYTctNzI3NC00NjE1LTlhYjktY2Q5MTdmMWFmNzcxXkEyXkFqcGc@._V1_UY500_AL_QL75_UX380_CR0,0,380,562_.jpg",
      "backdropImage": "https://m.media-amazon.com/images/M/MV5BNTkwNzJiYTctNzI3NC00NjE1LTlhYjktY2Q5MTdmMWFmNzcxXkEyXkFqcGc@._V1_UY1280_AL_QL75_UX380_CR0,0,380,562_.jpg",
      "year": 2026,
      "rating": 8.3,
      "genre": "Adventure, Comedy, Drama",
      "type": "movie",
      "maturity": "PG-13",
      "featured": true,
      "local": false
    },
    {
      "id": "imdb-tt32093575",
      "imdbId": "tt32093575",
      "title": "Scary Movie",
      "description": "Two friends find themselves caught up in mayhem involving killers, monsters and supernatural creatures once again.",
      "coverImage": "https://m.media-amazon.com/images/M/MV5BNTJjMDk1NzAtMGVmNS00NTFmLWFlOTQtZDk5M2I2NjZiZDdlXkEyXkFqcGc@._V1_UY500_AL_QL75_UX380_CR0,0,380,562_.jpg",
      "backdropImage": "https://m.media-amazon.com/images/M/MV5BNTJjMDk1NzAtMGVmNS00NTFmLWFlOTQtZDk5M2I2NjZiZDdlXkEyXkFqcGc@._V1_UY1280_AL_QL75_UX380_CR0,0,380,562_.jpg",
      "year": 2026,
      "rating": 0,
      "genre": "Comedy, Horror",
      "type": "movie",
      "maturity": "R",
      "featured": true,
      "local": false
    },
    {
      "id": "imdb-tt32547691",
      "imdbId": "tt32547691",
      "title": "Pressure",
      "description": "In the tense 72 hours before D-Day, General Dwight D. Eisenhower and Captain James Stagg face an impossible choice--launch the most dangerous seaborne invasion in history or risk losing the war altogether.",
      "coverImage": "https://m.media-amazon.com/images/M/MV5BYjkwMTkwYzItNTg4MC00OTc2LTk2Y2EtOGU3ZGE0NmQyYzdjXkEyXkFqcGc@._V1_UY500_AL_QL75_UX380_CR0,0,380,562_.jpg",
      "backdropImage": "https://m.media-amazon.com/images/M/MV5BYjkwMTkwYzItNTg4MC00OTc2LTk2Y2EtOGU3ZGE0NmQyYzdjXkEyXkFqcGc@._V1_UY1280_AL_QL75_UX380_CR0,0,380,562_.jpg",
      "year": 2026,
      "rating": 7.7,
      "genre": "Drama, History, Thriller",
      "type": "movie",
      "maturity": "PG-13",
      "featured": true,
      "local": false
    },
    {
      "id": "imdb-tt32273171",
      "imdbId": "tt32273171",
      "title": "The Death of Robin Hood",
      "description": "Grappling with his past after a life of crime and murder, Robin Hood finds himself gravely injured after a battle he thought would be his last. In the hands of a mysterious woman, he is offered a chance at salvation.",
      "coverImage": "https://m.media-amazon.com/images/M/MV5BYTRmNzlmZjEtYjkzMC00MmNjLThiOGYtZjM5MjFiZDQyM2IwXkEyXkFqcGc@._V1_UY500_AL_QL75_UX380_CR0,0,380,562_.jpg",
      "backdropImage": "https://m.media-amazon.com/images/M/MV5BYTRmNzlmZjEtYjkzMC00MmNjLThiOGYtZjM5MjFiZDQyM2IwXkEyXkFqcGc@._V1_UY1280_AL_QL75_UX380_CR0,0,380,562_.jpg",
      "year": 2026,
      "rating": 7.4,
      "genre": "Action, Adventure, Drama",
      "type": "movie",
      "maturity": "R",
      "featured": true,
      "local": false
    },
    {
      "id": "imdb-tt33764258",
      "imdbId": "tt33764258",
      "title": "The Odyssey",
      "description": "After the Trojan War, Odysseus faces a dangerous voyage back to Ithaca, meeting creatures like the Cyclops Polyphemus, Sirens, and Circe along the way.",
      "coverImage": "https://m.media-amazon.com/images/M/MV5BN2MyYjk2MWMtODMyZS00MDUyLWE0OGQtOTQ3MGY0MDE0ZjVmXkEyXkFqcGc@._V1_UY500_AL_QL75_UX380_CR0,20,380,562_.jpg",
      "backdropImage": "https://m.media-amazon.com/images/M/MV5BN2MyYjk2MWMtODMyZS00MDUyLWE0OGQtOTQ3MGY0MDE0ZjVmXkEyXkFqcGc@._V1_UY1280_AL_QL75_UX380_CR0,20,380,562_.jpg",
      "year": 2026,
      "rating": 0,
      "genre": "Action, Adventure, Fantasy",
      "type": "movie",
      "maturity": "N/A",
      "featured": true,
      "local": false
    },
    {
      "id": "imdb-tt8814476",
      "imdbId": "tt8814476",
      "title": "Supergirl",
      "description": "Kara Zor-El, aka Supergirl, joins forces with an unlikely companion on an interstellar journey of vengeance and justice when an unexpected adversary strikes too close to home.",
      "coverImage": "https://m.media-amazon.com/images/M/MV5BNjlhMTdmODYtOGE0ZC00YzAwLWI1NDMtMTIzZDQzZGVkNDMwXkEyXkFqcGc@._V1_UY500_AL_QL75_UY562_CR35,0,380,562_.jpg",
      "backdropImage": "https://m.media-amazon.com/images/M/MV5BNjlhMTdmODYtOGE0ZC00YzAwLWI1NDMtMTIzZDQzZGVkNDMwXkEyXkFqcGc@._V1_UY1280_AL_QL75_UY562_CR35,0,380,562_.jpg",
      "year": 2026,
      "rating": 0,
      "genre": "Action, Adventure, Drama",
      "type": "movie",
      "maturity": "PG-13",
      "featured": true,
      "local": false
    },
    {
      "id": "imdb-tt39143902",
      "imdbId": "tt39143902",
      "title": "Leviticus",
      "description": "Two teenage boys must escape a violent entity that takes the form of the person they desire most - each other.",
      "coverImage": "https://m.media-amazon.com/images/M/MV5BZjVkZjIxMzItMzYyMi00ODMwLWEwMWQtMjhhMTkwMGI5MWEyXkEyXkFqcGc@._V1_UY500_AL_QL75_UX380_CR0,0,380,562_.jpg",
      "backdropImage": "https://m.media-amazon.com/images/M/MV5BZjVkZjIxMzItMzYyMi00ODMwLWEwMWQtMjhhMTkwMGI5MWEyXkEyXkFqcGc@._V1_UY1280_AL_QL75_UX380_CR0,0,380,562_.jpg",
      "year": 2026,
      "rating": 5.3,
      "genre": "Horror, Romance, Sci-Fi",
      "type": "movie",
      "maturity": "R",
      "featured": true,
      "local": false
    },
    {
      "id": "imdb-tt31728330",
      "imdbId": "tt31728330",
      "title": "They Will Kill You",
      "description": "A woman takes a job as a housekeeper in a NYC high-rise, unaware of the building's history of disappearances. She soon realizes the community is shrouded in mystery.",
      "coverImage": "https://m.media-amazon.com/images/M/MV5BYjg5ZjQ0ZGQtMmY1NS00NTgyLTlkZWYtMDhlNzE3ZGY5ZDdmXkEyXkFqcGc@._V1_UY500_AL_QL75_UY562_CR35,0,380,562_.jpg",
      "backdropImage": "https://m.media-amazon.com/images/M/MV5BYjg5ZjQ0ZGQtMmY1NS00NTgyLTlkZWYtMDhlNzE3ZGY5ZDdmXkEyXkFqcGc@._V1_UY1280_AL_QL75_UY562_CR35,0,380,562_.jpg",
      "year": 2026,
      "rating": 6.5,
      "genre": "Action, Comedy, Horror",
      "type": "movie",
      "maturity": "R",
      "featured": true,
      "local": false
    },
    {
      "id": "imdb-tt33311069",
      "imdbId": "tt33311069",
      "title": "The Furious",
      "description": "A father fights fiercely against ruthless kidnappers to save his abducted daughter.",
      "coverImage": "https://m.media-amazon.com/images/M/MV5BODUyZjg2YzctNGE3Yi00YjhhLTkyZTItZTAwZTNhNDA1ODQzXkEyXkFqcGc@._V1_UY500_AL_QL75_UX380_CR0,4,380,562_.jpg",
      "backdropImage": "https://m.media-amazon.com/images/M/MV5BODUyZjg2YzctNGE3Yi00YjhhLTkyZTItZTAwZTNhNDA1ODQzXkEyXkFqcGc@._V1_UY1280_AL_QL75_UX380_CR0,4,380,562_.jpg",
      "year": 2026,
      "rating": 7.7,
      "genre": "Action, Crime, Thriller",
      "type": "movie",
      "maturity": "R",
      "featured": true,
      "local": false
    },
    {
      "id": "imdb-tt1979376",
      "imdbId": "tt1979376",
      "title": "Toy Story 4",
      "description": "When Woody, Buzz, and the gang join Bonnie on a road trip with her new craft project turned toy, Forky, the innocent little spork's antics launch Woody on a wild quest.",
      "coverImage": "https://m.media-amazon.com/images/M/MV5BMTYzMDM4NzkxOV5BMl5BanBnXkFtZTgwNzM1Mzg2NzM@._V1_UY500_AL_SX300.jpg",
      "backdropImage": "https://m.media-amazon.com/images/M/MV5BMTYzMDM4NzkxOV5BMl5BanBnXkFtZTgwNzM1Mzg2NzM@._V1_UY1280_AL_SX300.jpg",
      "year": 2019,
      "rating": 7.6,
      "genre": "Animation, Adventure, Comedy",
      "type": "movie",
      "maturity": "G",
      "featured": true,
      "local": false
    },
    {
      "id": "imdb-tt36958376",
      "imdbId": "tt36958376",
      "title": "Your Fault: London",
      "description": "A forbidden love story between 18-year-old Noah and stepbrother Nick faces challenges as they pursue different paths - him in business, her at Oxford - while dealing with new relationships and secrets.",
      "coverImage": "https://m.media-amazon.com/images/M/MV5BNzI2YmMxZWItNjlhOS00ODNmLWEzYjQtYWIyNjc0ZTQwOTZlXkEyXkFqcGc@._V1_UY500_AL_QL75_UX380_CR0,4,380,562_.jpg",
      "backdropImage": "https://m.media-amazon.com/images/M/MV5BNzI2YmMxZWItNjlhOS00ODNmLWEzYjQtYWIyNjc0ZTQwOTZlXkEyXkFqcGc@._V1_UY1280_AL_QL75_UX380_CR0,4,380,562_.jpg",
      "year": 2026,
      "rating": 6.2,
      "genre": "Drama, Romance",
      "type": "movie",
      "maturity": "TV-MA",
      "featured": true,
      "local": false
    },
    {
      "id": "imdb-tt1341338",
      "imdbId": "tt1341338",
      "title": "Good Luck, Have Fun, Don't Die",
      "description": "A \"Man From the Future\" arrives at a diner in Los Angeles where he must recruit the precise combination of disgruntled patrons to join him on a one-night quest to save the world from the terminal threat of a rogue artificial intel...",
      "coverImage": "https://m.media-amazon.com/images/M/MV5BOTQ0NzYzM2QtOWYzMC00MGU5LWJmMTQtYTU1ODU0ZjUwYjk0XkEyXkFqcGc@._V1_UY500_AL_QL75_UX380_CR0,0,380,562_.jpg",
      "backdropImage": "https://m.media-amazon.com/images/M/MV5BOTQ0NzYzM2QtOWYzMC00MGU5LWJmMTQtYTU1ODU0ZjUwYjk0XkEyXkFqcGc@._V1_UY1280_AL_QL75_UX380_CR0,0,380,562_.jpg",
      "year": 2026,
      "rating": 7,
      "genre": "Action, Adventure, Comedy",
      "type": "movie",
      "maturity": "R",
      "featured": true,
      "local": false
    },
    {
      "id": "imdb-tt34771210",
      "imdbId": "tt34771210",
      "title": "I Will Find You",
      "description": "A father imprisoned for his son's murder receives evidence suggesting his child may be alive, compelling him to escape and uncover the truth.",
      "coverImage": "https://m.media-amazon.com/images/M/MV5BYWFkOGU5ZTYtZTlhMi00NThiLWI3ZDEtMGQ2Y2UzNjlkZTUxXkEyXkFqcGc@._V1_UY500_AL_QL75_UX380_CR0,0,380,562_.jpg",
      "backdropImage": "https://m.media-amazon.com/images/M/MV5BYWFkOGU5ZTYtZTlhMi00NThiLWI3ZDEtMGQ2Y2UzNjlkZTUxXkEyXkFqcGc@._V1_UY1280_AL_QL75_UX380_CR0,0,380,562_.jpg",
      "year": 2026,
      "rating": 0,
      "genre": "Crime, Drama, Mystery",
      "type": "series",
      "maturity": "N/A",
      "featured": true,
      "local": false
    },
    {
      "id": "imdb-tt33332385",
      "imdbId": "tt33332385",
      "title": "Widow's Bay",
      "description": "A skeptical mayor leads the superstitious residents of a cursed New England island.",
      "coverImage": "https://m.media-amazon.com/images/M/MV5BYzE4ZDNkZWQtYTNmNy00MjQwLTk0ODItN2YyYWUwYzEzNzk2XkEyXkFqcGc@._V1_UY500_AL_QL75_UX380_CR0,4,380,562_.jpg",
      "backdropImage": "https://m.media-amazon.com/images/M/MV5BYzE4ZDNkZWQtYTNmNy00MjQwLTk0ODItN2YyYWUwYzEzNzk2XkEyXkFqcGc@._V1_UY1280_AL_QL75_UX380_CR0,4,380,562_.jpg",
      "year": 2026,
      "rating": 0,
      "genre": "Comedy, Drama, Horror",
      "type": "series",
      "maturity": "N/A",
      "featured": true,
      "local": false
    },
    {
      "id": "imdb-tt33546863",
      "imdbId": "tt33546863",
      "title": "Off Campus",
      "description": "A college-set romantic drama chronicling the unexpected love story between a music student and the university's star hockey player, exploring themes of love and the complexities of adulthood through deep friendships and enduring b...",
      "coverImage": "https://m.media-amazon.com/images/M/MV5BMDA0NzAzNDktYjBiOS00ZjFjLThhZTYtNzlkMDMzOTgxZTk5XkEyXkFqcGc@._V1_UY500_AL_QL75_UX380_CR0,4,380,562_.jpg",
      "backdropImage": "https://m.media-amazon.com/images/M/MV5BMDA0NzAzNDktYjBiOS00ZjFjLThhZTYtNzlkMDMzOTgxZTk5XkEyXkFqcGc@._V1_UY1280_AL_QL75_UX380_CR0,4,380,562_.jpg",
      "year": 2026,
      "rating": 8.2,
      "genre": "Drama, Romance, Sport",
      "type": "series",
      "maturity": "TV-MA",
      "featured": true,
      "local": false
    },
    {
      "id": "imdb-tt9813792",
      "imdbId": "tt9813792",
      "title": "From",
      "description": "A town with a hidden secret experiences strange occurrences that intensify at night. Mysterious forces disrupt everyday routines as residents try to preserve stability and community while attempting to comprehend their surroundings.",
      "coverImage": "https://m.media-amazon.com/images/M/MV5BNDAwNDljNWEtNWE1Zi00YjFlLWEzM2UtY2E3ZTM1MTcxMTcyXkEyXkFqcGc@._V1_UY500_AL_QL75_UX380_CR0,0,380,562_.jpg",
      "backdropImage": "https://m.media-amazon.com/images/M/MV5BNDAwNDljNWEtNWE1Zi00YjFlLWEzM2UtY2E3ZTM1MTcxMTcyXkEyXkFqcGc@._V1_UY1280_AL_QL75_UX380_CR0,0,380,562_.jpg",
      "year": 2022,
      "rating": 7.8,
      "genre": "Drama, Horror, Mystery",
      "type": "series",
      "maturity": "TV-MA",
      "featured": true,
      "local": false
    },
    {
      "id": "imdb-tt5607616",
      "imdbId": "tt5607616",
      "title": "Re: Zero - Starting Life in Another World",
      "description": "After being suddenly transported to another world, Subaru Natsuki and his new female partner are brutally murdered. However, Subaru awakens to a familiar scene, meeting the same girl again. The day begins to mysteriously repeat it...",
      "coverImage": "https://m.media-amazon.com/images/M/MV5BZWI4OTVkNDgtOTBmMC00M2I3LTk3NTctOWY3NmRkODIxMDViXkEyXkFqcGc@._V1_UY500_AL_SX300.jpg",
      "backdropImage": "https://m.media-amazon.com/images/M/MV5BZWI4OTVkNDgtOTBmMC00M2I3LTk3NTctOWY3NmRkODIxMDViXkEyXkFqcGc@._V1_UY1280_AL_SX300.jpg",
      "year": 2016,
      "rating": 8.1,
      "genre": "Animation, Adventure, Drama",
      "type": "series",
      "maturity": "TV-MA",
      "featured": true,
      "local": false
    },
    {
      "id": "imdb-tt34991493",
      "imdbId": "tt34991493",
      "title": "Dutton Ranch",
      "description": "Beth Dutton and Rip Wheeler fight to survive on their cherished 7,000-acre ranch amid tough times and stiff competition, while ensuring young Carter becomes the man he's supposed to be.",
      "coverImage": "https://m.media-amazon.com/images/M/MV5BZGM5NjFjYmUtOTljMS00ODlkLTk1MTktZjliNmIxNWE3NTViXkEyXkFqcGc@._V1_UY500_AL_QL75_UY562_CR35,0,380,562_.jpg",
      "backdropImage": "https://m.media-amazon.com/images/M/MV5BZGM5NjFjYmUtOTljMS00ODlkLTk1MTktZjliNmIxNWE3NTViXkEyXkFqcGc@._V1_UY1280_AL_QL75_UY562_CR35,0,380,562_.jpg",
      "year": 2026,
      "rating": 0,
      "genre": "Drama, Western",
      "type": "series",
      "maturity": "N/A",
      "featured": true,
      "local": false
    },
    {
      "id": "imdb-tt11198330",
      "imdbId": "tt11198330",
      "title": "House of the Dragon",
      "description": "An internal succession war within House Targaryen at the height of its power, 172 years before the birth of Daenerys Targaryen.",
      "coverImage": "https://m.media-amazon.com/images/M/MV5BZGM4MTczODQtNGIxOC00Y2U2LTk1YmItNzA2N2VhYmE0Y2YwXkEyXkFqcGc@._V1_UY500_AL_QL75_UX380_CR0,0,380,562_.jpg",
      "backdropImage": "https://m.media-amazon.com/images/M/MV5BZGM4MTczODQtNGIxOC00Y2U2LTk1YmItNzA2N2VhYmE0Y2YwXkEyXkFqcGc@._V1_UY1280_AL_QL75_UX380_CR0,0,380,562_.jpg",
      "year": 2022,
      "rating": 8.3,
      "genre": "Action, Adventure, Drama",
      "type": "series",
      "maturity": "TV-MA",
      "featured": true,
      "local": false
    },
    {
      "id": "imdb-tt34675596",
      "imdbId": "tt34675596",
      "title": "Cape Fear",
      "description": "A happily married couple faces a growing threat when a notorious killer from their past, Max Cady, is released from prison and seeks revenge.",
      "coverImage": "",
      "backdropImage": "",
      "year": 2025,
      "rating": 0,
      "genre": "Crime, Thriller",
      "type": "series",
      "maturity": "N/A",
      "featured": true,
      "local": false
    },
    {
      "id": "imdb-tt30460310",
      "imdbId": "tt30460310",
      "title": "Spider-Noir",
      "description": "An aging and down on his luck private investigator in 1930s New York is forced to grapple with his past life as the city's one and only superhero.",
      "coverImage": "https://m.media-amazon.com/images/M/MV5BYjU3NjEwNTItMzc1Mi00Y2QyLTljNDItOTQ4YjU4NjZjN2EyXkEyXkFqcGc@._V1_UY500_AL_QL75_UX380_CR0,4,380,562_.jpg",
      "backdropImage": "https://m.media-amazon.com/images/M/MV5BYjU3NjEwNTItMzc1Mi00Y2QyLTljNDItOTQ4YjU4NjZjN2EyXkEyXkFqcGc@._V1_UY1280_AL_QL75_UX380_CR0,4,380,562_.jpg",
      "year": 2026,
      "rating": 0,
      "genre": "Action, Adventure, Crime",
      "type": "series",
      "maturity": "N/A",
      "featured": true,
      "local": false
    },
    {
      "id": "imdb-tt27557289",
      "imdbId": "tt27557289",
      "title": "The Boroughs",
      "description": "In a seemingly picturesque retirement community, a group of unlikely heroes must band together to stop an otherworldly threat from stealing the one thing they don't have - time.",
      "coverImage": "https://m.media-amazon.com/images/M/MV5BNzU2ZGRmNjEtYmVkOC00Y2UwLTk2YmEtODY3ZWFiYjY0YTY1XkEyXkFqcGc@._V1_UY500_AL_QL75_UX380_CR0,0,380,562_.jpg",
      "backdropImage": "https://m.media-amazon.com/images/M/MV5BNzU2ZGRmNjEtYmVkOC00Y2UwLTk2YmEtODY3ZWFiYjY0YTY1XkEyXkFqcGc@._V1_UY1280_AL_QL75_UX380_CR0,0,380,562_.jpg",
      "year": 2026,
      "rating": 0,
      "genre": "Adventure, Drama, Fantasy",
      "type": "series",
      "maturity": "N/A",
      "featured": true,
      "local": false
    }
  ],
  "timestamp": 1782356007218,
  "source": "imdb-popularity-rank"
}